finite_dist/__init__.py
finite_dist/__init__.pyi
finite_dist/basics.py
finite_dist-0.1.0.dist-info/METADATA
finite_dist-0.1.0.dist-info/WHEEL
finite_dist-0.1.0.dist-info/top_level.txt
finite_dist-0.1.0.dist-info/RECORD
