Metadata-Version: 2.1
Name: finite-dist
Version: 0.1.0
Summary: Storing finite probability distributions as python counters
Author-email: Marcel Claramunt <marcel@moveread.com>
Project-URL: repo, https://github.com/moveread/REPO.git
Requires-Python: >=3.10
